README.rst
grungeera.zip
screenshot.png
setup.py
docs/HISTORY.txt
docs/INSTALL.txt
docs/LICENSE.GPL
docs/LICENSE.txt
plonetheme/__init__.py
plonetheme.grungeera.egg-info/PKG-INFO
plonetheme.grungeera.egg-info/SOURCES.txt
plonetheme.grungeera.egg-info/dependency_links.txt
plonetheme.grungeera.egg-info/entry_points.txt
plonetheme.grungeera.egg-info/namespace_packages.txt
plonetheme.grungeera.egg-info/not-zip-safe
plonetheme.grungeera.egg-info/requires.txt
plonetheme.grungeera.egg-info/top_level.txt
plonetheme/grungeera/__init__.py
plonetheme/grungeera/configure.zcml
plonetheme/grungeera/theme/grungeera/index.html
plonetheme/grungeera/theme/grungeera/rules.xml
plonetheme/grungeera/theme/grungeera/static/css/GrungeEra.css
plonetheme/grungeera/theme/grungeera/static/css/reset.css
plonetheme/grungeera/theme/grungeera/static/css/screen.css
plonetheme/grungeera/theme/grungeera/static/images/bg.jpg
plonetheme/grungeera/theme/grungeera/static/images/content-top.jpg
plonetheme/grungeera/theme/grungeera/static/images/content.jpg
plonetheme/grungeera/theme/grungeera/static/images/firefox-gray.jpg
plonetheme/grungeera/theme/grungeera/static/images/footer-bottom.jpg
plonetheme/grungeera/theme/grungeera/static/images/footer-sep.gif
plonetheme/grungeera/theme/grungeera/static/images/footer.jpg
plonetheme/grungeera/theme/grungeera/static/images/gravatar.jpg
plonetheme/grungeera/theme/grungeera/static/images/quote.gif
plonetheme/grungeera/theme/grungeera/static/images/search.gif
plonetheme/grungeera/theme/grungeera/static/images/sep.gif
plonetheme/grungeera/theme/grungeera/static/images/thumb.jpg